syncable/__init__.py
syncable/main.py
syncable-0.2.0.dist-info/licenses/LICENSE
syncable-0.2.0.dist-info/METADATA
syncable-0.2.0.dist-info/WHEEL
syncable-0.2.0.dist-info/top_level.txt
syncable-0.2.0.dist-info/RECORD
